LICENSE
MANIFEST.in
README.md
README.rst
requirements.txt
setup.cfg
setup.py
scapy_ssl_tls/__init__.py
scapy_ssl_tls/pkcs7.py
scapy_ssl_tls/ssl_tls.py
scapy_ssl_tls/ssl_tls_crypto.py
scapy_ssl_tls/ssl_tls_registry.py
scapy_ssl_tls.egg-info/PKG-INFO
scapy_ssl_tls.egg-info/SOURCES.txt
scapy_ssl_tls.egg-info/dependency_links.txt
scapy_ssl_tls.egg-info/requires.txt
scapy_ssl_tls.egg-info/top_level.txt