Metadata-Version: 1.1
Name: scapy-ssl-tls
Version: 1.2
Summary: An SSL/TLS layer for scapy the interactive packet manipulation tool
Home-page: https://github.com/tintinweb/scapy-ssl_tls/
Author: tintinweb
Author-email: tintinweb@oststrom.com
License: GPLv2
Download-URL: https://github.com/tintinweb/scapy-ssl_tls/tarball/v1.2
Keywords: scapy,ssl,tls,layer,network,dissect,packets,decrypt
Platform: UNKNOWN
